{
  "metadata": {
    "ctime": "1527109818", 
    "version": "1.0.0", 
    "user": "juan", 
    "mayaSceneFile": "/Users/juan/workspace/victor-animation/scenes/sandbox/Juan/Pose_Correction/Pose_Correction.ma", 
    "mayaVersion": "2018", 
    "description": ""
  }
,
  "objects": {
    "x:eyeCorner_L_innerBtm_ctrl": {
      "attrs": {
        "scaleX": {
          "type": "double", 
          "value": 0.8068970820609978
        }, 
        "scaleY": {
          "type": "double", 
          "value": 0.8956732192154107
        }
      }
    }, 
    "x:mech_eye_R_ctrl": {
      "attrs": {
        "translateX": {
          "type": "doubleLinear", 
          "value": 0.0
        }, 
        "translateY": {
          "type": "doubleLinear", 
          "value": 0.0
        }, 
        "GlowSize": {
          "type": "double", 
          "value": 0.5
        }, 
        "scaleX": {
          "type": "double", 
          "value": 1.0448486723224881
        }, 
        "scaleY": {
          "type": "double", 
          "value": 1.0448486723224881
        }, 
        "rotateZ": {
          "type": "doubleAngle", 
          "value": 0.0
        }, 
        "Lightness": {
          "type": "double", 
          "value": 1.0
        }
      }
    }, 
    "x:eyeCorner_L_innerTop_ctrl": {
      "attrs": {
        "scaleX": {
          "type": "double", 
          "value": 0.9303085523573559
        }, 
        "scaleY": {
          "type": "double", 
          "value": 1.0253287711531827
        }
      }
    }, 
    "x:mech_eyes_all_ctrl": {
      "attrs": {
        "On": {
          "type": "long", 
          "value": 1
        }, 
        "translateX": {
          "type": "doubleLinear", 
          "value": 0.0
        }, 
        "translateY": {
          "type": "doubleLinear", 
          "value": -0.01731841862996575
        }, 
        "scaleX": {
          "type": "double", 
          "value": 0.9955324472361298
        }, 
        "scaleY": {
          "type": "double", 
          "value": 0.8499948102031765
        }, 
        "rotateZ": {
          "type": "doubleAngle", 
          "value": 0.0
        }
      }
    }, 
    "x:eyeCorner_R_innerBtm_ctrl": {
      "attrs": {
        "scaleX": {
          "type": "double", 
          "value": 0.7668197725701896
        }, 
        "scaleY": {
          "type": "double", 
          "value": 0.8582427462377603
        }
      }
    }, 
    "x:eyeCorner_R_OuterBtm_ctrl": {
      "attrs": {
        "scaleX": {
          "type": "double", 
          "value": 0.8068970820609978
        }, 
        "scaleY": {
          "type": "double", 
          "value": 0.8956732192154107
        }
      }
    }, 
    "x:mech_L_pupil_ctrl": {
      "attrs": {
        "translateX": {
          "type": "doubleLinear", 
          "value": -0.060000000000000005
        }, 
        "translateY": {
          "type": "doubleLinear", 
          "value": 0.13237322561114961
        }
      }
    }, 
    "x:mech_lwrLid_L_ctrl": {
      "attrs": {
        "rotateZ": {
          "type": "doubleAngle", 
          "value": 0.0
        }, 
        "translateY": {
          "type": "doubleLinear", 
          "value": 0.0
        }, 
        "scaleY": {
          "type": "double", 
          "value": 1.0
        }
      }
    }, 
    "x:mech_eye_L_ctrl": {
      "attrs": {
        "translateX": {
          "type": "doubleLinear", 
          "value": 0.0
        }, 
        "translateY": {
          "type": "doubleLinear", 
          "value": 0.0
        }, 
        "GlowSize": {
          "type": "double", 
          "value": 0.5
        }, 
        "scaleX": {
          "type": "double", 
          "value": 1.0448486723224881
        }, 
        "scaleY": {
          "type": "double", 
          "value": 1.0448486723224881
        }, 
        "rotateZ": {
          "type": "doubleAngle", 
          "value": 0.0
        }, 
        "Lightness": {
          "type": "double", 
          "value": 1.0
        }
      }
    }, 
    "x:mech_upperLid_L_ctrl": {
      "attrs": {
        "rotateZ": {
          "type": "doubleAngle", 
          "value": 0.0
        }, 
        "translateY": {
          "type": "doubleLinear", 
          "value": -0.051301697703745125
        }, 
        "scaleY": {
          "type": "double", 
          "value": 1.0
        }
      }
    }, 
    "x:eyeCorner_L_OuterBtm_ctrl": {
      "attrs": {
        "scaleX": {
          "type": "double", 
          "value": 0.7668197725701896
        }, 
        "scaleY": {
          "type": "double", 
          "value": 0.8582427462377603
        }
      }
    }, 
    "x:mech_R_pupil_ctrl": {
      "attrs": {
        "translateX": {
          "type": "doubleLinear", 
          "value": 0.060000000000000005
        }, 
        "translateY": {
          "type": "doubleLinear", 
          "value": 0.13237322561114961
        }
      }
    }, 
    "x:eyeCorner_L_OuterTop_ctrl": {
      "attrs": {
        "scaleX": {
          "type": "double", 
          "value": 0.6956389307071127
        }, 
        "scaleY": {
          "type": "double", 
          "value": 0.8381872456932828
        }
      }
    }, 
    "x:eyeCorner_R_OuterTop_ctrl": {
      "attrs": {
        "scaleX": {
          "type": "double", 
          "value": 0.9303085523573559
        }, 
        "scaleY": {
          "type": "double", 
          "value": 1.0253287711531827
        }
      }
    }, 
    "x:eyeCorner_R_innerTop_ctrl": {
      "attrs": {
        "scaleX": {
          "type": "double", 
          "value": 0.6956389307071127
        }, 
        "scaleY": {
          "type": "double", 
          "value": 0.8381872456932828
        }
      }
    }, 
    "x:mech_upperLid_R_ctrl": {
      "attrs": {
        "rotateZ": {
          "type": "doubleAngle", 
          "value": 0.0
        }, 
        "translateY": {
          "type": "doubleLinear", 
          "value": -0.051301697703745125
        }, 
        "scaleY": {
          "type": "double", 
          "value": 1.0
        }
      }
    }, 
    "x:mech_lwrLid_R_ctrl": {
      "attrs": {
        "rotateZ": {
          "type": "doubleAngle", 
          "value": 0.0
        }, 
        "translateY": {
          "type": "doubleLinear", 
          "value": 0.0
        }, 
        "scaleY": {
          "type": "double", 
          "value": 1.0
        }
      }
    }
  }
}